{
  "item": [
    {
      "id": "e03bc11e-25e7-4968-8ffb-afaa511d8f46",
      "name": "Get",
      "request": {
        "name": "Get",
        "description": {},
        "url": {
          "path": ["health"],
          "host": ["{{baseUrl}}"],
          "query": [],
          "variable": []
        },
        "header": [
          {
            "key": "Accept",
            "value": "application/json"
          }
        ],
        "method": "GET",
        "auth": null
      },
      "response": [
        {
          "id": "3235bce8-95d0-4ca7-b441-e8c9a8b3b5cd",
          "name": "Ok",
          "originalRequest": {
            "url": {
              "path": ["health"],
              "host": ["{{baseUrl}}"],
              "query": [],
              "variable": []
            },
            "method": "GET",
            "body": {}
          },
          "status": "OK",
          "code": 200,
          "header": [
            {
              "key": "Content-Type",
              "value": "application/json"
            }
          ],
          "body": "{\n  \"status\": \"Ex\"\n}",
          "cookie": [],
          "_postman_previewlanguage": "json"
        }
      ],
      "event": []
    },
    {
      "id": "402f0371-6983-49d1-af9c-38438a118882",
      "name": "todos",
      "item": [
        {
          "id": "a7fed6ed-135c-4084-8149-e86bac75d08b",
          "name": "Get Todos",
          "request": {
            "name": "Get Todos",
            "description": {},
            "url": {
              "path": ["todos"],
              "host": ["{{baseUrl}}"],
              "query": [],
              "variable": []
            },
            "header": [
              {
                "key": "Accept",
                "value": "application/json"
              }
            ],
            "method": "GET",
            "auth": {
              "type": "oauth2"
            }
          },
          "response": [
            {
              "id": "3df8c417-7fde-4ffd-bd00-61a1a1078ab7",
              "name": "Ok",
              "originalRequest": {
                "url": {
                  "path": ["todos"],
                  "host": ["{{baseUrl}}"],
                  "query": [],
                  "variable": []
                },
                "header": [
                  {
                    "description": {
                      "content": "Added as a part of security scheme: oauth2",
                      "type": "text/plain"
                    },
                    "key": "Authorization",
                    "value": "<token>"
                  }
                ],
                "method": "GET",
                "body": {}
              },
              "status": "OK",
              "code": 200,
              "header": [
                {
                  "key": "Content-Type",
                  "value": "application/json"
                }
              ],
              "body": "[\n  {\n    \"status\": false,\n    \"todo\": \"laboris eu anim culpa\",\n    \"id\": \"ut proident incididunt\"\n  },\n  {\n    \"status\": false,\n    \"todo\": \"aute laboris et ullamco\",\n    \"id\": \"in dolore dolor\"\n  }\n]",
              "cookie": [],
              "_postman_previewlanguage": "json"
            }
          ],
          "event": []
        },
        {
          "id": "bb0aab16-835c-43bd-b828-d09a2353d474",
          "name": "Create Todo",
          "request": {
            "name": "Create Todo",
            "description": {},
            "url": {
              "path": ["todos"],
              "host": ["{{baseUrl}}"],
              "query": [],
              "variable": []
            },
            "header": [
              {
                "key": "Content-Type",
                "value": "application/json"
              },
              {
                "key": "Accept",
                "value": "application/json"
              }
            ],
            "method": "POST",
            "auth": {
              "type": "oauth2"
            },
            "body": {
              "mode": "raw",
              "raw": "{\n  \"todo\": \"<string>\"\n}",
              "options": {
                "raw": {
                  "language": "json"
                }
              }
            }
          },
          "response": [
            {
              "id": "1f984609-89db-4eb4-a0ed-5bf3ab9fdcb3",
              "name": "Ok",
              "originalRequest": {
                "url": {
                  "path": ["todos"],
                  "host": ["{{baseUrl}}"],
                  "query": [],
                  "variable": []
                },
                "header": [
                  {
                    "description": {
                      "content": "Added as a part of security scheme: oauth2",
                      "type": "text/plain"
                    },
                    "key": "Authorization",
                    "value": "<token>"
                  }
                ],
                "method": "POST",
                "body": {
                  "mode": "raw",
                  "raw": "{\n  \"todo\": \"<string>\"\n}",
                  "options": {
                    "raw": {
                      "language": "json"
                    }
                  }
                }
              },
              "status": "OK",
              "code": 200,
              "header": [
                {
                  "key": "Content-Type",
                  "value": "application/json"
                }
              ],
              "body": "{\n  \"status\": false,\n  \"todo\": \"in dolor\",\n  \"id\": \"Lorem ex\"\n}",
              "cookie": [],
              "_postman_previewlanguage": "json"
            }
          ],
          "event": [],
          "protocolProfileBehavior": {
            "disableBodyPruning": true
          }
        },
        {
          "id": "85194233-a334-4b51-a93e-087eeace0552",
          "name": "{id}",
          "item": [
            {
              "id": "74a6a6fd-d0b1-4d6a-944a-da2a20515f42",
              "name": "Get Todo",
              "request": {
                "name": "Get Todo",
                "description": {},
                "url": {
                  "path": ["todos", ":id"],
                  "host": ["{{baseUrl}}"],
                  "query": [],
                  "variable": [
                    {
                      "disabled": false,
                      "type": "any",
                      "value": "<string>",
                      "key": "id",
                      "description": "(Required) "
                    }
                  ]
                },
                "header": [
                  {
                    "key": "Accept",
                    "value": "application/json"
                  }
                ],
                "method": "GET",
                "auth": {
                  "type": "oauth2"
                }
              },
              "response": [
                {
                  "id": "65f8ebb7-b3ff-4a46-acc8-6b0412ec666f",
                  "name": "Ok",
                  "originalRequest": {
                    "url": {
                      "path": ["todos", ":id"],
                      "host": ["{{baseUrl}}"],
                      "query": [],
                      "variable": [
                        {
                          "disabled": false,
                          "type": "any",
                          "value": "<string>",
                          "key": "id",
                          "description": "(Required) "
                        }
                      ]
                    },
                    "header": [
                      {
                        "description": {
                          "content": "Added as a part of security scheme: oauth2",
                          "type": "text/plain"
                        },
                        "key": "Authorization",
                        "value": "<token>"
                      }
                    ],
                    "method": "GET",
                    "body": {}
                  },
                  "status": "OK",
                  "code": 200,
                  "header": [
                    {
                      "key": "Content-Type",
                      "value": "application/json"
                    }
                  ],
                  "body": "{\n  \"status\": false,\n  \"todo\": \"in dolor\",\n  \"id\": \"Lorem ex\"\n}",
                  "cookie": [],
                  "_postman_previewlanguage": "json"
                }
              ],
              "event": []
            },
            {
              "id": "64667eae-3f3d-4fbd-8bee-dcb710d1a73f",
              "name": "Update Todo",
              "request": {
                "name": "Update Todo",
                "description": {},
                "url": {
                  "path": ["todos", ":id"],
                  "host": ["{{baseUrl}}"],
                  "query": [],
                  "variable": [
                    {
                      "disabled": false,
                      "type": "any",
                      "value": "<string>",
                      "key": "id",
                      "description": "(Required) "
                    }
                  ]
                },
                "header": [
                  {
                    "key": "Content-Type",
                    "value": "application/json"
                  },
                  {
                    "key": "Accept",
                    "value": "application/json"
                  }
                ],
                "method": "PUT",
                "auth": {
                  "type": "oauth2"
                },
                "body": {
                  "mode": "raw",
                  "raw": "{\n  \"status\": \"<boolean>\",\n  \"todo\": \"<string>\"\n}",
                  "options": {
                    "raw": {
                      "language": "json"
                    }
                  }
                }
              },
              "response": [
                {
                  "id": "69e2b25e-f4df-48be-8ec3-5beb8558fb5b",
                  "name": "Ok",
                  "originalRequest": {
                    "url": {
                      "path": ["todos", ":id"],
                      "host": ["{{baseUrl}}"],
                      "query": [],
                      "variable": [
                        {
                          "disabled": false,
                          "type": "any",
                          "value": "<string>",
                          "key": "id",
                          "description": "(Required) "
                        }
                      ]
                    },
                    "header": [
                      {
                        "description": {
                          "content": "Added as a part of security scheme: oauth2",
                          "type": "text/plain"
                        },
                        "key": "Authorization",
                        "value": "<token>"
                      }
                    ],
                    "method": "PUT",
                    "body": {
                      "mode": "raw",
                      "raw": "{\n  \"status\": \"<boolean>\",\n  \"todo\": \"<string>\"\n}",
                      "options": {
                        "raw": {
                          "language": "json"
                        }
                      }
                    }
                  },
                  "status": "OK",
                  "code": 200,
                  "header": [
                    {
                      "key": "Content-Type",
                      "value": "application/json"
                    }
                  ],
                  "body": "{\n  \"status\": false,\n  \"todo\": \"in dolor\",\n  \"id\": \"Lorem ex\"\n}",
                  "cookie": [],
                  "_postman_previewlanguage": "json"
                }
              ],
              "event": [],
              "protocolProfileBehavior": {
                "disableBodyPruning": true
              }
            },
            {
              "id": "969d8c1a-4298-44f5-adc1-54080007a557",
              "name": "Patch Todo",
              "request": {
                "name": "Patch Todo",
                "description": {},
                "url": {
                  "path": ["todos", ":id"],
                  "host": ["{{baseUrl}}"],
                  "query": [],
                  "variable": [
                    {
                      "disabled": false,
                      "type": "any",
                      "value": "<string>",
                      "key": "id",
                      "description": "(Required) "
                    }
                  ]
                },
                "header": [
                  {
                    "key": "Content-Type",
                    "value": "application/json"
                  },
                  {
                    "key": "Accept",
                    "value": "application/json"
                  }
                ],
                "method": "PATCH",
                "auth": {
                  "type": "oauth2"
                },
                "body": {
                  "mode": "raw",
                  "raw": "{\n  \"status\": \"<boolean>\",\n  \"todo\": \"<string>\"\n}",
                  "options": {
                    "raw": {
                      "language": "json"
                    }
                  }
                }
              },
              "response": [
                {
                  "id": "96612b30-c368-44b2-bf97-b1a9ac6b77ed",
                  "name": "Ok",
                  "originalRequest": {
                    "url": {
                      "path": ["todos", ":id"],
                      "host": ["{{baseUrl}}"],
                      "query": [],
                      "variable": [
                        {
                          "disabled": false,
                          "type": "any",
                          "value": "<string>",
                          "key": "id",
                          "description": "(Required) "
                        }
                      ]
                    },
                    "header": [
                      {
                        "description": {
                          "content": "Added as a part of security scheme: oauth2",
                          "type": "text/plain"
                        },
                        "key": "Authorization",
                        "value": "<token>"
                      }
                    ],
                    "method": "PATCH",
                    "body": {
                      "mode": "raw",
                      "raw": "{\n  \"status\": \"<boolean>\",\n  \"todo\": \"<string>\"\n}",
                      "options": {
                        "raw": {
                          "language": "json"
                        }
                      }
                    }
                  },
                  "status": "OK",
                  "code": 200,
                  "header": [
                    {
                      "key": "Content-Type",
                      "value": "application/json"
                    }
                  ],
                  "body": "{\n  \"status\": false,\n  \"todo\": \"in dolor\",\n  \"id\": \"Lorem ex\"\n}",
                  "cookie": [],
                  "_postman_previewlanguage": "json"
                }
              ],
              "event": [],
              "protocolProfileBehavior": {
                "disableBodyPruning": true
              }
            },
            {
              "id": "50fd6f61-3f5e-4e40-bcb4-547eaf82557a",
              "name": "Delete Todo",
              "request": {
                "name": "Delete Todo",
                "description": {},
                "url": {
                  "path": ["todos", ":id"],
                  "host": ["{{baseUrl}}"],
                  "query": [],
                  "variable": [
                    {
                      "disabled": false,
                      "type": "any",
                      "value": "<string>",
                      "key": "id",
                      "description": "(Required) "
                    }
                  ]
                },
                "header": [
                  {
                    "key": "Accept",
                    "value": "application/json"
                  }
                ],
                "method": "DELETE",
                "auth": {
                  "type": "oauth2"
                }
              },
              "response": [
                {
                  "id": "bf24e182-afaa-4700-9acd-37967943c9ac",
                  "name": "Ok",
                  "originalRequest": {
                    "url": {
                      "path": ["todos", ":id"],
                      "host": ["{{baseUrl}}"],
                      "query": [],
                      "variable": [
                        {
                          "disabled": false,
                          "type": "any",
                          "value": "<string>",
                          "key": "id",
                          "description": "(Required) "
                        }
                      ]
                    },
                    "header": [
                      {
                        "description": {
                          "content": "Added as a part of security scheme: oauth2",
                          "type": "text/plain"
                        },
                        "key": "Authorization",
                        "value": "<token>"
                      }
                    ],
                    "method": "DELETE",
                    "body": {}
                  },
                  "status": "OK",
                  "code": 200,
                  "header": [
                    {
                      "key": "Content-Type",
                      "value": "application/json"
                    }
                  ],
                  "body": "{\n  \"deleted\": false\n}",
                  "cookie": [],
                  "_postman_previewlanguage": "json"
                }
              ],
              "event": []
            }
          ],
          "event": []
        }
      ],
      "event": []
    }
  ],
  "event": [],
  "variable": [
    {
      "type": "string",
      "value": "/",
      "key": "baseUrl"
    }
  ],
  "info": {
    "_postman_id": "07e65400-8af7-45bd-95b9-31cfb4967620",
    "name": "mongo-starter",
    "schema": "https://schema.getpostman.com/json/collection/v2.1.0/collection.json",
    "description": {
      "content": "MongoDB Starter\n\nContact Support:\n Name: hieudoanm \n Email: hieumdoan@gmail.com",
      "type": "text/plain"
    }
  }
}
